[{"id":1,"title":"Hello","picture":"","author":"John DOE","category":"food"},{"id":2,"title":"World","picture":"","author":"John DOE","category":"food"},{"id":3,"title":"Yeah","picture":"","author":"John DOE","category":"sport"},{"id":4,"title":"Blabla","picture":"","author":"Alexis","category":"sport"},{"id":5,"title":"Goodbye","picture":"","author":"John DOE","category":"food"},{"id":6,"title":"toto","author":"toto","category":"toto","picture":""},{"id":7,"title":"ezz","author":"ezaeza","category":"eze","picture":""},{"id":8,"title":"ss","author":"ss","category":"ss","picture":""},{"id":9,"title":"qsq","author":"sqsq","category":"sqsq","picture":""},{"id":10,"title":"$$","author":"$$","category":"$$$","picture":""},{"id":11,"title":"tr","author":"rr","category":"rr","picture":""},{"id":12,"title":"ezae","author":"ezae","category":"zaeza","picture":""},{"id":13,"title":"ytryr","author":"ytrytr","category":"ytrytr","picture":""},{"id":14,"title":"uyt","author":"uytuyt","category":"uytuyt","picture":""},{"id":15,"title":"z","author":"z","category":"z","picture":""},{"id":16,"title":"ss","author":"sss","category":"s","picture":""},{"id":17,"title":"test","author":"test","category":"test","picture":""},{"id":18,"title":"_","author":"_","category":"_","picture":""},{"id":19,"title":"sqs","author":"s","category":"s","picture":""},{"id":20,"title":"('","author":"ytr","category":"t","picture":""},{"id":21,"title":"z","author":"z","category":"z","picture":"public\\uploads\\9fab0aab3a96ecf152e85a5919840a9d.jpeg"},{"id":22,"title":"q","author":"q","category":"q","picture":"public\\uploads\\9fb90ba6d7f8e953ba72593f2260ab8f.jpeg"},{"id":23,"title":"trt","author":"t","category":"t","picture":"public\\uploads\\66f3f8c2404408fd1780c5f5187181b4.jpeg"},{"id":24,"title":"z","author":"z","category":"z","picture":"public\\uploads\\dfe3eda26113c1b976c03acfc2dd0a3f.jpeg"}]